pyworms/__init__.py
pyworms/utils.py
pyworms-0.4.0.dist-info/LICENSE.txt
pyworms-0.4.0.dist-info/METADATA
pyworms-0.4.0.dist-info/WHEEL
pyworms-0.4.0.dist-info/top_level.txt
pyworms-0.4.0.dist-info/RECORD
