Metadata-Version: 2.1
Name: pyworms
Version: 0.4.0
Summary: Python client for the WoRMS REST service
Author: Pieter Provoost
Author-email: pieterprovoost@gmail.com
License: BSD
License-File: LICENSE.txt
Requires-Dist: backports.functools-lru-cache
Requires-Dist: requests
